{
  "q0": {
    "q0": {
      "symbol": " ",
      "function": "None"
    },
    "q1": {
      "symbol": "a-z",
      "function": "COLLECT_VARIABLE_NAME"
    }
  },
  "q1": {
    "q1": {
      "symbol": "a-z,0-9",
      "function": "COLLECT_VARIABLE_NAME"
    },
    "q2": {
      "symbol": " ",
      "function": "None"
    },
    "q3": {
      "symbol": "=",
      "function": "ADD_OPERATION"
    }
  },
  "q2": {
    "q2": {
      "symbol": " ",
      "function": "None"
    },
    "q3": {
      "symbol": "=",
      "function": "ADD_OPERATION"
    }
  },
  "q3": {
    "q3": {
      "symbol": " ,(",
      "function": "ADD_OPERATION"
    },
    "q4": {
      "symbol": "a-z",
      "function": "COLLECT_VARIABLE_NAME"
    },
    "q5": {
      "symbol": "0-9",
      "function": "COLLECT_VARIABLE_NAME"
    }
  },
  "q4": {
    "q3": {
      "symbol": "+,*",
      "function": "ADD_OPERATION"
    },
    "q4": {
      "symbol": "a-z,0-9",
      "function": "COLLECT_VARIABLE_NAME"
    },
    "q6": {
      "symbol": " ,)",
      "function": "ADD_OPERATION"
    }
  },
  "q5": {
    "q3": {
      "symbol": "+,*",
      "function": "ADD_OPERATION"
    },
    "q5": {
      "symbol": "0-9",
      "function": "COLLECT_VARIABLE_NAME"
    },
    "q6": {
      "symbol": " ,)",
      "function": "ADD_OPERATION"
    },
    "q7": {
      "symbol": ".",
      "function": "COLLECT_VARIABLE_NAME"
    },
    "q8": {
      "symbol": "e",
      "function": "COLLECT_VARIABLE_NAME"
    }
  },
  "q6": {
    "q3": {
      "symbol": "+,*",
      "function": "ADD_OPERATION"
    },
    "q6": {
      "symbol": " ,)",
      "function": "ADD_OPERATION"
    }
  },
  "q7": {
    "q9": {
      "symbol": "0-9",
      "function": "COLLECT_VARIABLE_NAME"
    }
  },
  "q8": {
    "q10": {
      "symbol": "+,-",
      "function": "COLLECT_VARIABLE_NAME"
    },
    "q11": {
      "symbol": "0-9",
      "function": "COLLECT_VARIABLE_NAME"
    }
  },
  "q9": {
    "q3": {
      "symbol": "+,*",
      "function": "ADD_OPERATION"
    },
    "q8": {
      "symbol": "e",
      "function": "COLLECT_VARIABLE_NAME"
    },
    "q9": {
      "symbol": "0-9",
      "function": "COLLECT_VARIABLE_NAME"
    }
  },
  "q10": {
    "q11": {
      "symbol": "0-9",
      "function": "COLLECT_VARIABLE_NAME"
    }
  },
  "q11": {
    "q3": {
      "symbol": "+,*",
      "function": "ADD_OPERATION"
    },
    "q6": {
      "symbol": " ,)",
      "function": "ADD_OPERATION"
    },
    "q11": {
      "symbol": "0-9",
      "function": "COLLECT_VARIABLE_NAME"
    }
  }
}